{
  "Model": "Fireball",
  "Config": "Projectile_Config_Empty_Silent",
  "ProjectileCount": 1,
  "SpreadAmount": 3,
  "BulletSpeed": 25,
  "BulletDistance": 500,
  "DamageCalculator": {
    "Class": "Light",
    "BaseDamage": {
      "Projectile": 8
    }
  },
  "DamageEffects": {
    "WorldParticles": [
      {
        "SystemId": "Explosion_Small",
        "PositionOffset": {
          "X": 0,
          "Y": 0
        }
      }
    ]
  },
  "BlockHitParticles": [
    {
      "SystemId": "Explosion_Small",
      "PositionOffset": {
        "X": 0,
        "Y": 0
      }
    }
  ]
}
